gamutrf/__init__.py
gamutrf/__main__.py
gamutrf/compress_dirs.py
gamutrf/dc_spike.py
gamutrf/ettus_source.py
gamutrf/flask_handler.py
gamutrf/grinferenceoutput.py
gamutrf/grpduzmq.py
gamutrf/grscan.py
gamutrf/grsource.py
gamutrf/mqtt_reporter.py
gamutrf/offline.py
gamutrf/sample_reader.py
gamutrf/scan.py
gamutrf/soapy_source.py
gamutrf/utils.py
gamutrf-0.5.71.dist-info/LICENSE
gamutrf-0.5.71.dist-info/METADATA
gamutrf-0.5.71.dist-info/WHEEL
gamutrf-0.5.71.dist-info/entry_points.txt
gamutrf-0.5.71.dist-info/RECORD
