Metadata-Version: 2.1
Name: gamutrf
Version: 0.5.71
Summary: An orchestrated SDR scanner
License: Apache-2.0
Author: cglewis
Author-email: clewis@iqt.org
Requires-Python: >=3.10,<3.13
Classifier: License :: OSI Approved :: Apache Software License
Classifier: Programming Language :: Python :: 3
Classifier: Programming Language :: Python :: 3.10
Classifier: Programming Language :: Python :: 3.11
Classifier: Programming Language :: Python :: 3.12
Requires-Dist: Flask (==3.0.3)
Requires-Dist: Jinja2 (==3.1.4)
Requires-Dist: bjoern (==3.2.2)
Requires-Dist: falcon (==3.1.3)
Requires-Dist: falcon-cors (==1.1.7)
Requires-Dist: gpsd-py3 (==0.3.0)
Requires-Dist: numpy (==2.1.1)
Requires-Dist: paho-mqtt (==2.1.0)
Requires-Dist: pandas (==2.2.2)
Requires-Dist: pbr (==6.1.0)
Requires-Dist: prometheus_client (==0.20.0)
Requires-Dist: pyzmq (==26.2.0)
Requires-Dist: requests (==2.32.3)
Requires-Dist: scipy (==1.14.1)
Requires-Dist: sigmf (==1.2.2)
Requires-Dist: sysrsync (==1.1.1)
Requires-Dist: webcolors (==24.8.0)
Requires-Dist: zstandard (==0.23.0)
Project-URL: homepage, https://github.com/IQTLabs/gamutRF
